[
{"position": [40.681281, -8.599817], "speed": 0},
{"position": [40.6801, -8.59663], "speed": 0.373},
{"position": [40.67981, -8.59594], "speed": 4.144},
{"position": [40.67907, -8.59096], "speed": 14.998},
{"position": [40.68029, -8.59877], "speed": 17.385},
{"position": [40.67714, -8.5988], "speed": 7.885},
{"position": [40.67613, -8.59245], "speed": 0.109},
{"position": [40.67959, -8.59078], "speed": 5.197},
{"position": [40.68067, -8.59978], "speed": 15.86},
{"position": [40.67665, -8.59586], "speed": 16.821},
{"position": [40.6773, -8.5927], "speed": 6.704},
{"position": [40.67678, -8.59411], "speed": 0.002},
{"position": [40.67724, -8.59944], "speed": 6.318},
{"position": [40.67854, -8.59941], "speed": 16.602},
{"position": [40.68084, -8.59359], "speed": 16.121},
{"position": [40.68115, -8.59242], "speed": 5.564},
{"position": [40.67923, -8.59246], "speed": 0.056},
{"position": [40.67874, -8.59543], "speed": 7.488},
{"position": [40.67757, -8.59308], "speed": 17.213},
{"position": [40.67668, -8.59692], "speed": 15.298},
{"position": [40.67618, -8.59632], "speed": 4.486},
{"position": [40.68031, -8.59724], "speed": 0.268},
{"position": [40.67915, -8.59561], "speed": 8.686},
{"position": [40.67972, -8.59447], "speed": 17.68},
{"position": [40.67613, -8.59085], "speed": 14.365},
{"position": [40.67633, -8.5983], "speed": 3.489},
{"position": [40.67804, -8.59349], "speed": 0.635},
{"position": [40.67756, -8.59502], "speed": 9.891},
{"position": [40.67871, -8.59219], "speed": 17.997},
{"position": [40.6766, -8.59877], "speed": 13.339},
{"position": [40.67754, -8.59323], "speed": 2.591},
{"position": [40.67731, -8.59511], "speed": 1.151},
{"position": [40.6807, -8.59591], "speed": 11.082},
{"position": [40.67844, -8.5979], "speed": 18.156},
{"position": [40.67715, -8.59679], "speed": 12.238},
{"position": [40.67734, -8.594], "speed": 1.807},
{"position": [40.67694, -8.59149], "speed": 1.807},
{"position": [40.67897, -8.59644], "speed": 12.238},
{"position": [40.67683, -8.59023], "speed": 18.156},
{"position": [40.68085, -8.5936], "speed": 11.083},
{"position": [40.67884, -8.59575], "speed": 1.151},
{"position": [40.67742, -8.59105], "speed": 2.591},
{"position": [40.67753, -8.59478], "speed": 13.339},
{"position": [40.67735, -8.5955], "speed": 17.997},
{"position": [40.67852, -8.59981], "speed": 9.891},
{"position": [40.68067, -8.59649], "speed": 0.635},
{"position": [40.67643, -8.59314], "speed": 3.489},
{"position": [40.67722, -8.59551], "speed": 14.365},
{"position": [40.68067, -8.59856], "speed": 17.68},
{"position": [40.67808, -8.59269], "speed": 8.686},
{"position": [40.67619, -8.59406], "speed": 0.268},
{"position": [40.67649, -8.59535], "speed": 4.486},
{"position": [40.68111, -8.59635], "speed": 15.297},
{"position": [40.68022, -8.5934], "speed": 17.213},
{"position": [40.67757, -8.59352], "speed": 7.488},
{"position": [40.67971, -8.59742], "speed": 0.056},
{"position": [40.67982, -8.59836], "speed": 5.564},
{"position": [40.68012, -8.59415], "speed": 16.121},
{"position": [40.67808, -8.59395], "speed": 16.603},
{"position": [40.67657, -8.59145], "speed": 6.318},
{"position": [40.67739, -8.59107], "speed": 0.002},
{"position": [40.68109, -8.59298], "speed": 6.703},
{"position": [40.67797, -8.59713], "speed": 16.821},
{"position": [40.67655, -8.59044], "speed": 15.86},
{"position": [40.67813, -8.5976], "speed": 5.197},
{"position": [40.67738, -8.59018], "speed": 0.109},
{"position": [40.67618, -8.5954], "speed": 7.885},
{"position": [40.68085, -8.59151], "speed": 17.385},
{"position": [40.67968, -8.59349], "speed": 14.998},
{"position": [40.6783, -8.59332], "speed": 4.144},
{"position": [40.67694, -8.59045], "speed": 0.373},
{"position": [40.67761, -8.59775], "speed": 9.088},
{"position": [40.67931, -8.59913], "speed": 17.803},
{"position": [40.67767, -8.59667], "speed": 14.032},
{"position": [40.67794, -8.59617], "speed": 3.178},
{"position": [40.67947, -8.59698], "speed": 0.791},
{"position": [40.67658, -8.59753], "speed": 10.291},
{"position": [40.67992, -8.59423], "speed": 18.067},
{"position": [40.67697, -8.59224], "speed": 12.98},
{"position": [40.67826, -8.59573], "speed": 2.317},
{"position": [40.67606, -8.590134], "speed": 0},
{"position": [40.67606, -8.590134], "speed": 0},
{"position": [40.66954, -8.58258], "speed": 1.15},
{"position": [40.65906, -8.5875], "speed": 12.764},
{"position": [40.66266, -8.58832], "speed": 46.196},
{"position": [40.66082, -8.57985], "speed": 53.549},
{"position": [40.66316, -8.58767], "speed": 24.288},
{"position": [40.67464, -8.58199], "speed": 0.335},
{"position": [40.65999, -8.58173], "speed": 16.007},
{"position": [40.6642, -8.58849], "speed": 48.851},
{"position": [40.66431, -8.58], "speed": 51.812},
{"position": [40.67191, -8.58028], "speed": 20.648},
{"position": [40.66071, -8.58327], "speed": 0.007},
{"position": [40.65654, -8.58238], "speed": 19.46},
{"position": [40.65628, -8.58015], "speed": 51.138},
{"position": [40.66003, -8.58534], "speed": 49.656},
{"position": [40.66068, -8.58429], "speed": 17.138},
{"position": [40.65927, -8.58364], "speed": 0.171},
{"position": [40.6671, -8.58953], "speed": 23.064},
{"position": [40.66179, -8.58769], "speed": 53.018},
{"position": [40.66486, -8.58014], "speed": 47.119},
{"position": [40.67187, -8.58955], "speed": 13.818},
{"position": [40.65923, -8.58192], "speed": 0.825},
{"position": [40.65736, -8.58664], "speed": 26.754},
{"position": [40.66967, -8.58838], "speed": 54.458},
{"position": [40.67169, -8.58728], "speed": 44.246},
{"position": [40.66505, -8.58713], "speed": 10.748},
{"position": [40.66252, -8.58503], "speed": 1.957},
{"position": [40.67489, -8.58777], "speed": 30.467},
{"position": [40.66212, -8.58865], "speed": 55.433},
{"position": [40.66698, -8.58697], "speed": 41.086},
{"position": [40.65704, -8.5876], "speed": 7.981},
{"position": [40.66591, -8.58937], "speed": 3.546},
{"position": [40.66217, -8.58946], "speed": 34.135},
{"position": [40.67222, -8.58306], "speed": 55.924},
{"position": [40.65892, -8.58366], "speed": 37.697},
{"position": [40.664, -8.58661], "speed": 5.567},
{"position": [40.65865, -8.58714], "speed": 5.566},
{"position": [40.6661, -8.59011], "speed": 37.696},
{"position": [40.65967, -8.58938], "speed": 55.924},
{"position": [40.66862, -8.57998], "speed": 34.136},
{"position": [40.66452, -8.58418], "speed": 3.547},
{"position": [40.65756, -8.5824], "speed": 7.981},
{"position": [40.65616, -8.58417], "speed": 41.086},
{"position": [40.67089, -8.58121], "speed": 55.433},
{"position": [40.66132, -8.58149], "speed": 30.467},
{"position": [40.67559, -8.58539], "speed": 1.957},
{"position": [40.67562, -8.58933], "speed": 10.747},
{"position": [40.65968, -8.58905], "speed": 44.245},
{"position": [40.66974, -8.58852], "speed": 54.459},
{"position": [40.658, -8.58353], "speed": 26.755},
{"position": [40.66636, -8.58512], "speed": 0.825},
{"position": [40.67444, -8.58757], "speed": 13.818},
{"position": [40.65682, -8.58673], "speed": 47.119},
{"position": [40.6559, -8.58994], "speed": 53.019},
{"position": [40.67166, -8.58833], "speed": 23.065},
{"position": [40.65668, -8.58567], "speed": 0.171},
{"position": [40.664, -8.58135], "speed": 17.137},
{"position": [40.66944, -8.58669], "speed": 49.656},
{"position": [40.66508, -8.57997], "speed": 51.139},
{"position": [40.67184, -8.58075], "speed": 19.461},
{"position": [40.66535, -8.58801], "speed": 0.007},
{"position": [40.65836, -8.58939], "speed": 20.647},
{"position": [40.66158, -8.5832], "speed": 51.812},
{"position": [40.655693, -8.57946], "speed": 0},
{"position": [40.655693, -8.57946], "speed": 0},
{"position": [40.65536, -8.58032], "speed": 1.023},
{"position": [40.6548, -8.58599], "speed": 11.351},
{"position": [40.65506, -8.58963], "speed": 41.082},
{"position": [40.65284, -8.58867], "speed": 47.62},
{"position": [40.6546, -8.58052], "speed": 21.599},
{"position": [40.65379, -8.58048], "speed": 0.298},
{"position": [40.65467, -8.58544], "speed": 14.235},
{"position": [40.65557, -8.58029], "speed": 43.443},
{"position": [40.65406, -8.57961], "speed": 46.076},
{"position": [40.65292, -8.58644], "speed": 18.362},
{"position": [40.6536, -8.58464], "speed": 0.006},
{"position": [40.65545, -8.58143], "speed": 17.306},
{"position": [40.65397, -8.58487], "speed": 45.477},
{"position": [40.65346, -8.59002], "speed": 44.159},
{"position": [40.65532, -8.58441], "speed": 15.24},
{"position": [40.65375, -8.58298], "speed": 0.152},
{"position": [40.65266, -8.58592], "speed": 20.511},
{"position": [40.6553, -8.58284], "speed": 47.149},
{"position": [40.65324, -8.57991], "speed": 41.903},
{"position": [40.65502, -8.58471], "speed": 12.288},
{"position": [40.65424, -8.58056], "speed": 0.733},
{"position": [40.65333, -8.58857], "speed": 23.792},
{"position": [40.65352, -8.58002], "speed": 48.429},
{"position": [40.65524, -8.58944], "speed": 39.347},
{"position": [40.65488, -8.58573], "speed": 9.558},
{"position": [40.65451, -8.58473], "speed": 1.74},
{"position": [40.65431, -8.58311], "speed": 27.094},
{"position": [40.65484, -8.58482], "speed": 49.296},
{"position": [40.65237, -8.590167], "speed": 0},
{"position": [40.65237, -8.590167], "speed": 0},
{"position": [40.64842, -8.61487], "speed": 0.641},
{"position": [40.64308, -8.61548], "speed": 7.111},
{"position": [40.64934, -8.59584], "speed": 25.736},
{"position": [40.65048, -8.60433], "speed": 29.832},
{"position": [40.64833, -8.60084], "speed": 13.531},
{"position": [40.6479, -8.62048], "speed": 0.187},
{"position": [40.65054, -8.61083], "speed": 8.917},
{"position": [40.6485, -8.60011], "speed": 27.215},
{"position": [40.64801, -8.6088], "speed": 28.864},
{"position": [40.65235, -8.62089], "speed": 11.503},
{"position": [40.6489, -8.61674], "speed": 0.004},
{"position": [40.64845, -8.60828], "speed": 10.841},
{"position": [40.6471, -8.60895], "speed": 28.489},
{"position": [40.64285, -8.60239], "speed": 27.663},
{"position": [40.64546, -8.59373], "speed": 9.547},
{"position": [40.64614, -8.60825], "speed": 0.095},
{"position": [40.64394, -8.5939], "speed": 12.849},
{"position": [40.65077, -8.59805], "speed": 29.537},
{"position": [40.6473, -8.59593], "speed": 26.25},
{"position": [40.64658, -8.59451], "speed": 7.698},
{"position": [40.64441, -8.60779], "speed": 0.459},
{"position": [40.6484, -8.60773], "speed": 14.905},
{"position": [40.65113, -8.59769], "speed": 30.339},
{"position": [40.65015, -8.61272], "speed": 24.649},
{"position": [40.64841, -8.60566], "speed": 5.988},
{"position": [40.64655, -8.61072], "speed": 1.09},
{"position": [40.64781, -8.60624], "speed": 16.973},
{"position": [40.65077, -8.5948], "speed": 30.881},
{"position": [40.64828, -8.59347], "speed": 22.889},
{"position": [40.65082, -8.60972], "speed": 4.446},
{"position": [40.6466, -8.59291], "speed": 1.976},
{"position": [40.64789, -8.61752], "speed": 19.017},
{"position": [40.64293, -8.60864], "speed": 31.155},
{"position": [40.64873, -8.59425], "speed": 21.001},
{"position": [40.64359, -8.60219], "speed": 3.101},
{"position": [40.64747, -8.59773], "speed": 3.101},
{"position": [40.64652, -8.60064], "speed": 21.0},
{"position": [40.648, -8.59104], "speed": 31.155},
{"position": [40.64324, -8.6214], "speed": 19.017},
{"position": [40.64608, -8.61951], "speed": 1.976},
{"position": [40.64633, -8.59376], "speed": 4.446},
{"position": [40.6443, -8.59228], "speed": 22.889},
{"position": [40.65146, -8.61092], "speed": 30.882},
{"position": [40.64479, -8.61981], "speed": 16.973},
{"position": [40.64664, -8.59355], "speed": 1.09},
{"position": [40.65185, -8.61382], "speed": 5.987},
{"position": [40.65143, -8.61712], "speed": 24.649},
{"position": [40.64337, -8.60782], "speed": 30.339},
{"position": [40.65139, -8.61691], "speed": 14.905},
{"position": [40.64494, -8.61143], "speed": 0.46},
{"position": [40.64924, -8.59776], "speed": 7.698},
{"position": [40.6453, -8.61413], "speed": 26.25},
{"position": [40.64989, -8.61699], "speed": 29.537},
{"position": [40.64453, -8.5997], "speed": 12.849},
{"position": [40.64805, -8.59493], "speed": 0.095},
{"position": [40.64785, -8.6004], "speed": 9.547},
{"position": [40.64402, -8.61707], "speed": 27.663},
{"position": [40.64834, -8.59249], "speed": 28.489},
{"position": [40.64646, -8.5932], "speed": 10.842},
{"position": [40.6503, -8.59503], "speed": 0.004},
{"position": [40.64602, -8.60831], "speed": 11.503},
{"position": [40.64441, -8.59516], "speed": 28.864},
{"position": [40.64604, -8.61571], "speed": 27.215},
{"position": [40.6443, -8.6209], "speed": 8.918},
{"position": [40.64958, -8.61817], "speed": 0.187},
{"position": [40.651, -8.60018], "speed": 13.53},
{"position": [40.65132, -8.59535], "speed": 29.832},
{"position": [40.6433, -8.59492], "speed": 25.736},
{"position": [40.6494, -8.60013], "speed": 7.111},
{"position": [40.64659, -8.61667], "speed": 0.64},
{"position": [40.64479, -8.59462], "speed": 15.594},
{"position": [40.64906, -8.59936], "speed": 30.549},
{"position": [40.64553, -8.60644], "speed": 24.079},
{"position": [40.64943, -8.60568], "speed": 5.454},
{"position": [40.6455, -8.61137], "speed": 1.357},
{"position": [40.64889, -8.61029], "speed": 17.658},
{"position": [40.64537, -8.59293], "speed": 31.003},
{"position": [40.65108, -8.59269], "speed": 22.273},
{"position": [40.6478, -8.59094], "speed": 3.975},
{"position": [40.64993, -8.60565], "speed": 2.325},
{"position": [40.65089, -8.61732], "speed": 19.686},
{"position": [40.64751, -8.6136], "speed": 31.186},
{"position": [40.64523, -8.59967], "speed": 20.349},
{"position": [40.65143, -8.59042], "speed": 2.701},
{"position": [40.64619, -8.59055], "speed": 3.526},
{"position": [40.6505, -8.59632], "speed": 21.642},
{"position": [40.64582, -8.60461], "speed": 31.094},
{"position": [40.64773, -8.59718], "speed": 18.341},
{"position": [40.64966, -8.59024], "speed": 1.653},
{"position": [40.64399, -8.62199], "speed": 4.939},
{"position": [40.645, -8.60565], "speed": 23.491},
{"position": [40.6466, -8.59444], "speed": 30.73},
{"position": [40.64383, -8.60797], "speed": 16.285},
{"position": [40.64867, -8.61941], "speed": 0.851},
{"position": [40.64908, -8.61837], "speed": 6.54},
{"position": [40.64736, -8.59666], "speed": 25.201},
{"position": [40.64726, -8.61571], "speed": 30.1},
{"position": [40.64528, -8.60684], "speed": 14.217},
{"position": [40.6493, -8.61463], "speed": 0.308},
{"position": [40.65028, -8.60735], "speed": 8.3},
{"position": [40.6477, -8.61344], "speed": 26.743},
{"position": [40.64347, -8.61947], "speed": 29.214},
{"position": [40.64508, -8.59192], "speed": 12.173},
{"position": [40.64638, -8.5905], "speed": 0.034},
{"position": [40.6477, -8.60726], "speed": 10.188},
{"position": [40.64822, -8.59567], "speed": 28.088},
{"position": [40.64846, -8.60064], "speed": 28.089},
{"position": [40.64502, -8.59751], "speed": 10.19},
{"position": [40.64864, -8.59401], "speed": 0.034},
{"position": [40.64525, -8.59258], "speed": 12.172},
{"position": [40.65051, -8.61908], "speed": 29.213},
{"position": [40.64524, -8.6081], "speed": 26.744},
{"position": [40.64476, -8.61542], "speed": 8.301},
{"position": [40.6437, -8.60692], "speed": 0.308},
{"position": [40.65029, -8.61987], "speed": 14.216},
{"position": [40.64453, -8.61533], "speed": 30.099},
{"position": [40.64474, -8.60263], "speed": 25.203},
{"position": [40.64563, -8.61546], "speed": 6.541},
{"position": [40.64926, -8.59505], "speed": 0.851},
{"position": [40.64537, -8.60189], "speed": 16.284},
{"position": [40.64615, -8.61614], "speed": 30.73},
{"position": [40.65121, -8.6143], "speed": 23.492},
{"position": [40.65228, -8.62109], "speed": 4.94},
{"position": [40.64407, -8.60712], "speed": 1.653},
{"position": [40.64535, -8.60152], "speed": 18.34},
{"position": [40.65216, -8.59794], "speed": 31.094},
{"position": [40.65147, -8.60467], "speed": 21.643},
{"position": [40.64824, -8.59095], "speed": 3.527},
{"position": [40.65049, -8.61013], "speed": 2.7},
{"position": [40.65066, -8.59427], "speed": 20.347},
{"position": [40.64377, -8.6016], "speed": 31.186},
{"position": [40.64448, -8.61057], "speed": 19.687},
{"position": [40.65217, -8.60255], "speed": 2.326},
{"position": [40.64276, -8.622132], "speed": 0},
{"position": [40.64276, -8.622132], "speed": 0},
{"position": [40.64264, -8.6221], "speed": 0.035},
{"position": [40.64267, -8.62189], "speed": 0.393},
{"position": [40.64264, -8.62199], "speed": 1.422},
{"position": [40.64266, -8.62185], "speed": 1.648},
{"position": [40.64272, -8.62187], "speed": 0.747},
{"position": [40.64264, -8.62189], "speed": 0.01},
{"position": [40.64276, -8.62211], "speed": 0.493},
{"position": [40.64268, -8.62211], "speed": 1.503},
{"position": [40.64274, -8.6218], "speed": 1.594},
{"position": [40.64264, -8.62177], "speed": 0.635},
{"position": [40.64262, -8.62205], "speed": 0.0},
{"position": [40.64267, -8.62203], "speed": 0.599},
{"position": [40.64272, -8.62207], "speed": 1.574},
{"position": [40.6427, -8.62179], "speed": 1.528},
{"position": [40.64264, -8.62209], "speed": 0.527},
{"position": [40.64271, -8.62181], "speed": 0.005},
{"position": [40.64275, -8.62187], "speed": 0.71},
{"position": [40.64269, -8.62211], "speed": 1.631},
{"position": [40.64261, -8.62189], "speed": 1.45},
{"position": [40.64264, -8.62181], "speed": 0.425},
{"position": [40.64257, -8.62207], "speed": 0.025},
{"position": [40.64266, -8.62211], "speed": 0.823},
{"position": [40.64263, -8.62187], "speed": 1.676},
{"position": [40.64262, -8.62209], "speed": 1.362},
{"position": [40.64269, -8.62208], "speed": 0.331},
{"position": [40.64276, -8.62194], "speed": 0.06},
{"position": [40.64269, -8.62185], "speed": 0.938},
{"position": [40.64263, -8.62192], "speed": 1.706},
{"position": [40.6426, -8.62181], "speed": 1.264},
{"position": [40.64273, -8.62181], "speed": 0.246},
{"position": [40.64261, -8.62188], "speed": 0.109},
{"position": [40.64257, -8.621762], "speed": 0},
{"position": [40.64257, -8.621762], "speed": 0},
{"position": [40.644, -8.62188], "speed": 2.199},
{"position": [40.64584, -8.62815], "speed": 24.412},
{"position": [40.64463, -8.62942], "speed": 88.353},
{"position": [40.64426, -8.62243], "speed": 102.415},
{"position": [40.64718, -8.62802], "speed": 46.452},
{"position": [40.64738, -8.62407], "speed": 0.641},
{"position": [40.64404, -8.62724], "speed": 30.614},
{"position": [40.64825, -8.62948], "speed": 93.43},
{"position": [40.6444, -8.62578], "speed": 99.094},
{"position": [40.64508, -8.62993], "speed": 39.491},
{"position": [40.64335, -8.62191], "speed": 0.013},
{"position": [40.64544, -8.62547], "speed": 37.219},
{"position": [40.648439, -8.630391], "speed": 0},
{"position": [40.648439, -8.630391], "speed": 0},
{"position": [40.6483, -8.63272], "speed": 0.509},
{"position": [40.64759, -8.63252], "speed": 5.654},
{"position": [40.64832, -8.63271], "speed": 20.461},
{"position": [40.64818, -8.63208], "speed": 23.718},
{"position": [40.64824, -8.6326], "speed": 10.758},
{"position": [40.64834, -8.63093], "speed": 0.148},
{"position": [40.64793, -8.63211], "speed": 7.09},
{"position": [40.64824, -8.63081], "speed": 21.637},
{"position": [40.64827, -8.63071], "speed": 22.949},
{"position": [40.64833, -8.63172], "speed": 9.146},
{"position": [40.64766, -8.6317], "speed": 0.003},
{"position": [40.6482, -8.63198], "speed": 8.619},
{"position": [40.64785, -8.63132], "speed": 22.65},
{"position": [40.647499, -8.632877], "speed": 0},
{"position": [40.647499, -8.632877], "speed": 0},
{"position": [40.64673, -8.63298], "speed": 0.55},
{"position": [40.64739, -8.63421], "speed": 6.105},
{"position": [40.64743, -8.63329], "speed": 22.094},
{"position": [40.64693, -8.63368], "speed": 25.61},
{"position": [40.64732, -8.63463], "speed": 11.616},
{"position": [40.64739, -8.63434], "speed": 0.16},
{"position": [40.64695, -8.63342], "speed": 7.655},
{"position": [40.64711, -8.63402], "speed": 23.363},
{"position": [40.64736, -8.63331], "speed": 24.779},
{"position": [40.646678, -8.634712], "speed": 0},
{"position": [40.646678, -8.634712], "speed": 0},
{"position": [40.64341, -8.6397], "speed": 0.799},
{"position": [40.64431, -8.63625], "speed": 8.868},
{"position": [40.64376, -8.63893], "speed": 32.095},
{"position": [40.6449, -8.64337], "speed": 37.204},
{"position": [40.64483, -8.63866], "speed": 16.874},
{"position": [40.64412, -8.636], "speed": 0.233},
{"position": [40.64374, -8.64047], "speed": 11.121},
{"position": [40.64566, -8.63803], "speed": 33.94},
{"position": [40.64368, -8.64435], "speed": 35.997},
{"position": [40.64534, -8.64227], "speed": 14.346},
{"position": [40.64345, -8.63501], "speed": 0.005},
{"position": [40.64622, -8.63614], "speed": 13.52},
{"position": [40.64504, -8.63935], "speed": 35.529},
{"position": [40.64499, -8.63922], "speed": 34.499},
{"position": [40.64621, -8.64078], "speed": 11.907},
{"position": [40.64535, -8.63714], "speed": 0.119},
{"position": [40.64344, -8.63756], "speed": 16.024},
{"position": [40.64373, -8.64066], "speed": 36.835},
{"position": [40.64389, -8.63614], "speed": 32.737},
{"position": [40.64599, -8.63517], "speed": 9.6},
{"position": [40.6436, -8.64421], "speed": 0.573},
{"position": [40.64636, -8.63957], "speed": 18.588},
{"position": [40.64406, -8.64489], "speed": 37.835},
{"position": [40.64624, -8.63734], "speed": 30.74},
{"position": [40.64517, -8.6389], "speed": 7.467},
{"position": [40.64382, -8.63995], "speed": 1.359},
{"position": [40.6434, -8.6431], "speed": 21.167},
{"position": [40.64408, -8.64], "speed": 38.512},
{"position": [40.64488, -8.64442], "speed": 28.545},
{"position": [40.64641, -8.63699], "speed": 5.545},
{"position": [40.64598, -8.63582], "speed": 2.464},
{"position": [40.64342, -8.63608], "speed": 23.716},
{"position": [40.64603, -8.64396], "speed": 38.854},
{"position": [40.64451, -8.63924], "speed": 26.19},
{"position": [40.6434, -8.64491], "speed": 0},
{"position": [40.6434, -8.64491], "speed": 0},
{"position": [40.64306, -8.64501], "speed": 0.537},
{"position": [40.64298, -8.64521], "speed": 5.956},
{"position": [40.64331, -8.64507], "speed": 21.556},
{"position": [40.64293, -8.645], "speed": 24.987},
{"position": [40.643, -8.64738], "speed": 11.333},
{"position": [40.64332, -8.64713], "speed": 0.156},
{"position": [40.64329, -8.64629], "speed": 7.469},
{"position": [40.64332, -8.64506], "speed": 22.795},
{"position": [40.64327, -8.6467], "speed": 24.176},
{"position": [40.64309, -8.64626], "speed": 9.635},
{"position": [40.64323, -8.64705], "speed": 0.003},
{"position": [40.64324, -8.64524], "speed": 9.081},
{"position": [40.64289, -8.6475], "speed": 0},
{"position": [40.64289, -8.6475], "speed": 0},
{"position": [40.64219, -8.65055], "speed": 0.438},
{"position": [40.64201, -8.65154], "speed": 4.86},
{"position": [40.64252, -8.65087], "speed": 17.59},
{"position": [40.64288, -8.65024], "speed": 20.389},
{"position": [40.64265, -8.64995], "speed": 9.248},
{"position": [40.64276, -8.65104], "speed": 0.128},
{"position": [40.64211, -8.65128], "speed": 6.095},
{"position": [40.64206, -8.64927], "speed": 18.6},
{"position": [40.64225, -8.64832], "speed": 19.728},
{"position": [40.64218, -8.65055], "speed": 7.862},
{"position": [40.64258, -8.65086], "speed": 0.003},
{"position": [40.64284, -8.64857], "speed": 7.41},
{"position": [40.64232, -8.64773], "speed": 19.471},
{"position": [40.64273, -8.65119], "speed": 18.907},
{"position": [40.64252, -8.64901], "speed": 6.525},
{"position": [40.64236, -8.64904], "speed": 0.065},
{"position": [40.64264, -8.65112], "speed": 8.782},
{"position": [40.64225, -8.64911], "speed": 20.187},
{"position": [40.64278, -8.64759], "speed": 17.941},
{"position": [40.64206, -8.65084], "speed": 5.261},
{"position": [40.64259, -8.6485], "speed": 0.314},
{"position": [40.64286, -8.65131], "speed": 10.187},
{"position": [40.64215, -8.64826], "speed": 20.735},
{"position": [40.64202, -8.65112], "speed": 16.847},
{"position": [40.64223, -8.65013], "speed": 4.092},
{"position": [40.64195, -8.65185], "speed": 0},
{"position": [40.64195, -8.65185], "speed": 0},
{"position": [40.64185, -8.65259], "speed": 0.382},
{"position": [40.64091, -8.65215], "speed": 4.236},
{"position": [40.64129, -8.65252], "speed": 15.332},
{"position": [40.64147, -8.65214], "speed": 17.772},
{"position": [40.64158, -8.65258], "speed": 8.061},
{"position": [40.64121, -8.6522], "speed": 0.111},
{"position": [40.64098, -8.6523], "speed": 5.312},
{"position": [40.64095, -8.65269], "speed": 16.213},
{"position": [40.64138, -8.6528], "speed": 17.196},
{"position": [40.64164, -8.65255], "speed": 6.853},
{"position": [40.64093, -8.65241], "speed": 0.002},
{"position": [40.641, -8.65224], "speed": 6.459},
{"position": [40.64081, -8.65299], "speed": 0},
{"position": [40.64081, -8.65299], "speed": 0},
{"position": [40.63848, -8.65265], "speed": 0.689},
{"position": [40.6405, -8.65296], "speed": 7.646},
{"position": [40.63853, -8.65199], "speed": 27.674},
{"position": [40.63902, -8.65185], "speed": 32.079},
{"position": [40.64046, -8.65231], "speed": 14.55},
{"position": [40.64025, -8.65191], "speed": 0.201},
{"position": [40.63982, -8.65188], "speed": 9.589},
{"position": [40.64042, -8.65291], "speed": 29.264},
{"position": [40.6387, -8.65259], "speed": 31.038},
{"position": [40.63995, -8.65191], "speed": 12.37},
{"position": [40.64067, -8.65261], "speed": 0.004},
{"position": [40.64032, -8.65281], "speed": 11.658},
{"position": [40.63834, -8.6518], "speed": 0},
{"position": [40.63834, -8.6518], "speed": 0},
{"position": [40.63742, -8.65604], "speed": 0.442},
{"position": [40.63701, -8.653], "speed": 4.906},
{"position": [40.63723, -8.6535], "speed": 17.754},
{"position": [40.63547, -8.65255], "speed": 20.58},
{"position": [40.63747, -8.65407], "speed": 9.335},
{"position": [40.63828, -8.65228], "speed": 0.129},
{"position": [40.63484, -8.65593], "speed": 6.152},
{"position": [40.6359, -8.65454], "speed": 18.775},
{"position": [40.6366, -8.65408], "speed": 19.913},
{"position": [40.63702, -8.65192], "speed": 7.936},
{"position": [40.63595, -8.6523], "speed": 0.003},
{"position": [40.63804, -8.65547], "speed": 7.479},
{"position": [40.63742, -8.65475], "speed": 19.654},
{"position": [40.63757, -8.65286], "speed": 19.084},
{"position": [40.63803, -8.65553], "speed": 6.586},
{"position": [40.638, -8.65185], "speed": 0.066},
{"position": [40.63658, -8.65478], "speed": 8.864},
{"position": [40.63681, -8.65492], "speed": 20.376},
{"position": [40.63662, -8.65211], "speed": 18.109},
{"position": [40.63691, -8.65365], "speed": 5.311},
{"position": [40.63586, -8.6556], "speed": 0.317},
{"position": [40.63827, -8.65611], "speed": 10.282},
{"position": [40.63752, -8.65531], "speed": 20.93},
{"position": [40.63726, -8.65306], "speed": 17.005},
{"position": [40.63643, -8.65501], "speed": 4.131},
{"position": [40.63791, -8.65449], "speed": 0.752},
{"position": [40.63738, -8.65549], "speed": 11.709},
{"position": [40.63797, -8.65613], "speed": 21.304},
{"position": [40.63663, -8.65216], "speed": 15.791},
{"position": [40.63735, -8.65264], "speed": 3.067},
{"position": [40.63782, -8.65413], "speed": 1.363},
{"position": [40.63672, -8.65431], "speed": 13.119},
{"position": [40.6379, -8.6537], "speed": 21.493},
{"position": [40.63503, -8.65308], "speed": 14.488},
{"position": [40.63763, -8.65607], "speed": 2.139},
{"position": [40.63569, -8.65486], "speed": 2.139},
{"position": [40.63474, -8.65619], "speed": 0},
{"position": [40.63474, -8.65619], "speed": 0},
{"position": [40.63154, -8.6549], "speed": 0.629},
{"position": [40.63103, -8.65545], "speed": 6.985},
{"position": [40.63201, -8.65609], "speed": 25.281},
{"position": [40.63473, -8.65568], "speed": 29.305},
{"position": [40.63283, -8.65432], "speed": 13.292},
{"position": [40.63411, -8.65421], "speed": 0.183},
{"position": [40.63276, -8.65585], "speed": 8.76},
{"position": [40.63455, -8.65471], "speed": 26.734},
{"position": [40.63109, -8.65592], "speed": 28.354},
{"position": [40.63302, -8.65505], "speed": 11.3},
{"position": [40.63288, -8.65399], "speed": 0.004},
{"position": [40.63254, -8.65411], "speed": 10.65},
{"position": [40.6344, -8.65474], "speed": 27.985},
{"position": [40.63077, -8.6546], "speed": 27.174},
{"position": [40.63368, -8.65562], "speed": 9.379},
{"position": [40.63462, -8.65535], "speed": 0.094},
{"position": [40.63078, -8.65566], "speed": 12.622},
{"position": [40.63377, -8.65411], "speed": 29.014},
{"position": [40.63245, -8.65448], "speed": 25.786},
{"position": [40.63272, -8.65404], "speed": 7.562},
{"position": [40.63267, -8.65362], "speed": 0.451},
{"position": [40.63188, -8.65581], "speed": 14.641},
{"position": [40.63224, -8.65559], "speed": 29.802},
{"position": [40.63076, -8.65341], "speed": 0},
{"position": [40.63076, -8.65341], "speed": 0},
{"position": [40.62865, -8.6526], "speed": 0.439},
{"position": [40.62841, -8.65261], "speed": 4.876},
{"position": [40.62762, -8.65227], "speed": 17.648},
{"position": [40.62834, -8.65193], "speed": 20.457},
{"position": [40.62926, -8.6519], "speed": 9.278},
{"position": [40.62807, -8.65306], "speed": 0.128},
{"position": [40.62922, -8.65244], "speed": 6.115},
{"position": [40.62743, -8.65272], "speed": 18.662},
{"position": [40.63068, -8.65143], "speed": 19.793},
{"position": [40.62812, -8.65221], "speed": 7.888},
{"position": [40.62922, -8.65153], "speed": 0.003},
{"position": [40.62962, -8.65315], "speed": 7.434},
{"position": [40.63008, -8.65325], "speed": 19.536},
{"position": [40.62807, -8.65288], "speed": 18.97},
{"position": [40.62749, -8.65298], "speed": 6.547},
{"position": [40.62965, -8.65289], "speed": 0.065},
{"position": [40.63005, -8.65174], "speed": 8.811},
{"position": [40.63029, -8.65281], "speed": 20.254},
{"position": [40.62996, -8.65146], "speed": 18.001},
{"position": [40.62885, -8.65185], "speed": 5.279},
{"position": [40.62814, -8.65191], "speed": 0.315},
{"position": [40.62893, -8.65131], "speed": 10.221},
{"position": [40.62879, -8.65339], "speed": 20.804},
{"position": [40.63022, -8.65299], "speed": 16.903},
{"position": [40.62999, -8.65127], "speed": 4.106},
{"position": [40.63031, -8.65234], "speed": 0.747},
{"position": [40.62982, -8.65248], "speed": 11.639},
{"position": [40.62848, -8.65248], "speed": 21.176},
{"position": [40.62732, -8.651202], "speed": 0},
{"position": [40.62732, -8.651202], "speed": 0},
{"position": [40.62732, -8.6512], "speed": 0.0},
{"position": [40.62732, -8.6512], "speed": 0.0},
{"position": [40.62732, -8.6512], "speed": 0.0},
{"position": [40.62732, -8.6512], "speed": 0.0},
{"position": [40.62732, -8.6512], "speed": 0.0},
{"position": [40.62732, -8.6512], "speed": 0.0},
{"position": [40.62732, -8.6512], "speed": 0.0},
{"position": [40.62732, -8.6512], "speed": 0.0},
{"position": [40.62732, -8.6512], "speed": 0.0},
{"position": [40.62732, -8.6512], "speed": 0.0},
{"position": [40.62732, -8.6512], "speed": 0.0},
{"position": [40.62732, -8.6512], "speed": 0.0},
{"position": [40.62732, -8.6512], "speed": 0.0},
{"position": [40.62732, -8.6512], "speed": 0.0},
{"position": [40.62732, -8.6512], "speed": 0.0},
{"position": [40.62732, -8.6512], "speed": 0.0},
{"position": [40.62732, -8.6512], "speed": 0.0},
{"position": [40.62732, -8.6512], "speed": 0.0},
{"position": [40.62732, -8.6512], "speed": 0.0},
{"position": [40.62732, -8.6512], "speed": 0.0},
{"position": [40.62732, -8.6512], "speed": 0.0},
{"position": [40.62732, -8.6512], "speed": 0.0},
{"position": [40.62732, -8.6512], "speed": 0.0},
{"position": [40.62732, -8.6512], "speed": 0.0},
{"position": [40.62732, -8.6512], "speed": 0.0},
{"position": [40.62732, -8.6512], "speed": 0.0},
{"position": [40.62732, -8.6512], "speed": 0.0},
{"position": [40.62732, -8.6512], "speed": 0.0},
{"position": [40.62732, -8.6512], "speed": 0.0},
{"position": [40.62732, -8.6512], "speed": 0.0},
{"position": [40.62732, -8.6512], "speed": 0.0},
{"position": [40.62732, -8.6512], "speed": 0.0},
{"position": [40.62732, -8.6512], "speed": 0.0},
{"position": [40.62732, -8.6512], "speed": 0.0},
{"position": [40.62732, -8.6512], "speed": 0.0},
{"position": [40.62732, -8.6512], "speed": 0.0},
{"position": [40.62732, -8.651202], "speed": 0},
{"position": [40.62732, -8.651202], "speed": 0},
{"position": [40.62879, -8.65289], "speed": 0.506},
{"position": [40.62978, -8.65301], "speed": 5.613},
{"position": [40.62738, -8.65311], "speed": 20.316},
{"position": [40.62963, -8.65225], "speed": 23.549},
{"position": [40.62892, -8.65193], "speed": 10.681},
{"position": [40.6305, -8.65301], "speed": 0.147},
{"position": [40.62822, -8.65306], "speed": 7.039},
{"position": [40.62795, -8.65271], "speed": 21.483},
{"position": [40.62918, -8.65323], "speed": 22.785},
{"position": [40.62997, -8.65293], "speed": 9.08},
{"position": [40.62996, -8.65197], "speed": 0.003},
{"position": [40.62776, -8.65273], "speed": 8.558},
{"position": [40.62762, -8.65151], "speed": 22.489},
{"position": [40.62941, -8.65244], "speed": 21.837},
{"position": [40.6278, -8.6516], "speed": 7.537},
{"position": [40.62968, -8.65149], "speed": 0.075},
{"position": [40.62734, -8.65242], "speed": 10.143},
{"position": [40.62838, -8.65291], "speed": 23.316},
{"position": [40.62989, -8.65252], "speed": 20.722},
{"position": [40.62844, -8.65214], "speed": 6.077},
{"position": [40.62829, -8.65183], "speed": 0.363},
{"position": [40.62741, -8.65215], "speed": 11.766},
{"position": [40.63067, -8.65192], "speed": 23.949},
{"position": [40.63011, -8.65154], "speed": 19.458},
{"position": [40.63083, -8.65325], "speed": 0},
{"position": [40.63083, -8.65325], "speed": 0},
{"position": [40.63183, -8.6541], "speed": 0.346},
{"position": [40.63429, -8.6544], "speed": 3.841},
{"position": [40.63242, -8.65352], "speed": 13.902},
{"position": [40.6325, -8.65542], "speed": 16.115},
{"position": [40.63106, -8.65482], "speed": 7.309},
{"position": [40.63128, -8.65428], "speed": 0.101},
{"position": [40.63314, -8.65387], "speed": 4.817},
{"position": [40.63303, -8.65437], "speed": 14.701},
{"position": [40.63443, -8.65435], "speed": 15.592},
{"position": [40.63196, -8.65558], "speed": 6.214},
{"position": [40.6341, -8.65538], "speed": 0.002},
{"position": [40.63124, -8.65408], "speed": 5.856},
{"position": [40.63086, -8.65559], "speed": 15.39},
{"position": [40.63409, -8.65456], "speed": 14.944},
{"position": [40.63266, -8.65501], "speed": 5.157},
{"position": [40.63488, -8.65355], "speed": 0.051},
{"position": [40.63432, -8.65419], "speed": 6.941},
{"position": [40.6329, -8.65351], "speed": 15.955},
{"position": [40.63101, -8.65385], "speed": 14.18},
{"position": [40.6327, -8.65544], "speed": 4.158},
{"position": [40.6322, -8.65436], "speed": 0.248},
{"position": [40.63092, -8.65528], "speed": 8.052},
{"position": [40.63095, -8.65501], "speed": 16.389},
{"position": [40.63115, -8.65568], "speed": 13.315},
{"position": [40.6349, -8.65516], "speed": 3.235},
{"position": [40.63192, -8.6543], "speed": 0.589},
{"position": [40.63196, -8.65488], "speed": 9.169},
{"position": [40.63228, -8.65454], "speed": 16.682},
{"position": [40.63122, -8.65333], "speed": 12.365},
{"position": [40.6315, -8.65336], "speed": 2.402},
{"position": [40.63273, -8.65537], "speed": 1.067},
{"position": [40.63303, -8.65367], "speed": 10.273},
{"position": [40.63205, -8.65439], "speed": 16.83},
{"position": [40.63452, -8.6554], "speed": 11.344},
{"position": [40.63472, -8.65566], "speed": 1.675},
{"position": [40.63242, -8.65381], "speed": 1.675},
{"position": [40.63237, -8.65517], "speed": 11.344},
{"position": [40.63183, -8.65551], "speed": 16.83},
{"position": [40.63278, -8.65346], "speed": 10.273},
{"position": [40.63342, -8.65458], "speed": 1.067},
{"position": [40.63457, -8.65386], "speed": 2.402},
{"position": [40.63334, -8.6551], "speed": 12.364},
{"position": [40.634901, -8.655725], "speed": 0},
{"position": [40.634901, -8.655725], "speed": 0},
{"position": [40.63515, -8.65238], "speed": 0.447},
{"position": [40.63627, -8.65286], "speed": 4.967},
{"position": [40.63658, -8.65488], "speed": 17.978},
{"position": [40.63549, -8.65288], "speed": 20.839},
{"position": [40.63643, -8.65411], "speed": 9.452},
{"position": [40.63531, -8.65429], "speed": 0.13},
{"position": [40.63684, -8.65539], "speed": 6.229},
{"position": [40.63671, -8.65404], "speed": 19.011},
{"position": [40.6355, -8.65248], "speed": 20.163},
{"position": [40.63742, -8.65237], "speed": 8.036},
{"position": [40.63763, -8.65445], "speed": 0.003},
{"position": [40.63737, -8.65411], "speed": 7.573},
{"position": [40.63758, -8.65413], "speed": 19.901},
{"position": [40.63609, -8.65373], "speed": 19.324},
{"position": [40.63765, -8.65552], "speed": 6.669},
{"position": [40.635, -8.65265], "speed": 0.067},
{"position": [40.63711, -8.65341], "speed": 8.976},
{"position": [40.63722, -8.65216], "speed": 20.633},
{"position": [40.63514, -8.65452], "speed": 18.337},
{"position": [40.63614, -8.6533], "speed": 5.378},
{"position": [40.636, -8.65489], "speed": 0.321},
{"position": [40.63493, -8.65562], "speed": 10.412},
{"position": [40.6361, -8.6547], "speed": 21.193},
{"position": [40.63764, -8.65373], "speed": 17.219},
{"position": [40.63683, -8.65421], "speed": 4.183},
{"position": [40.63707, -8.65335], "speed": 0.761},
{"position": [40.6375, -8.65232], "speed": 11.857},
{"position": [40.63633, -8.65487], "speed": 21.572},
{"position": [40.637783, -8.652141], "speed": 0},
{"position": [40.637783, -8.652141], "speed": 0},
{"position": [40.63877, -8.65122], "speed": 0.551},
{"position": [40.6399, -8.6515], "speed": 6.122},
{"position": [40.63782, -8.652], "speed": 22.155},
{"position": [40.63988, -8.65163], "speed": 25.682},
{"position": [40.63873, -8.65177], "speed": 11.648},
{"position": [40.63918, -8.65171], "speed": 0.161},
{"position": [40.6378, -8.65206], "speed": 7.677},
{"position": [40.63869, -8.65182], "speed": 23.428},
{"position": [40.63795, -8.65124], "speed": 24.849},
{"position": [40.63799, -8.65165], "speed": 9.903},
{"position": [40.63886, -8.65135], "speed": 0.003},
{"position": [40.63834, -8.65164], "speed": 9.333},
{"position": [40.63868, -8.65165], "speed": 24.525},
{"position": [40.639977, -8.65117], "speed": 0},
{"position": [40.639977, -8.65117], "speed": 0},
{"position": [40.64132, -8.65123], "speed": 0.619},
{"position": [40.64008, -8.65151], "speed": 6.876},
{"position": [40.64022, -8.65143], "speed": 24.887},
{"position": [40.64058, -8.65183], "speed": 28.848},
{"position": [40.64066, -8.65201], "speed": 13.084},
{"position": [40.64119, -8.65187], "speed": 0.18},
{"position": [40.64065, -8.6515], "speed": 8.623},
{"position": [40.64094, -8.65187], "speed": 26.317},
{"position": [40.63999, -8.65163], "speed": 27.912},
{"position": [40.641752, -8.652012], "speed": 0},
{"position": [40.641752, -8.652012], "speed": 0},
{"position": [40.64209, -8.65194], "speed": 0.478},
{"position": [40.64227, -8.6516], "speed": 5.304},
{"position": [40.64263, -8.65179], "speed": 19.195},
{"position": [40.6418, -8.6484], "speed": 22.25},
{"position": [40.64259, -8.64774], "speed": 10.092},
{"position": [40.64239, -8.6505], "speed": 0.139},
{"position": [40.64201, -8.64922], "speed": 6.651},
{"position": [40.64197, -8.64994], "speed": 20.297},
{"position": [40.64255, -8.64848], "speed": 21.528},
{"position": [40.64187, -8.64854], "speed": 8.579},
{"position": [40.64253, -8.65063], "speed": 0.003},
{"position": [40.64191, -8.6481], "speed": 8.086},
{"position": [40.64178, -8.65005], "speed": 21.248},
{"position": [40.64185, -8.65087], "speed": 20.632},
{"position": [40.64228, -8.65113], "speed": 7.121},
{"position": [40.64214, -8.64748], "speed": 0.071},
{"position": [40.64211, -8.64993], "speed": 9.583},
{"position": [40.6423, -8.64957], "speed": 22.029},
{"position": [40.64188, -8.64869], "speed": 19.578},
{"position": [40.64183, -8.64791], "speed": 5.741},
{"position": [40.64186, -8.64717], "speed": 0.343},
{"position": [40.64234, -8.64859], "speed": 11.116},
{"position": [40.64211, -8.64822], "speed": 22.627},
{"position": [40.64222, -8.649], "speed": 18.384},
{"position": [40.64245, -8.65174], "speed": 4.466},
{"position": [40.64266, -8.65179], "speed": 0.813},
{"position": [40.64272, -8.647147], "speed": 0},
{"position": [40.64272, -8.647147], "speed": 0},
{"position": [40.64293, -8.64604], "speed": 0.487},
{"position": [40.64286, -8.64568], "speed": 5.41},
{"position": [40.64288, -8.64559], "speed": 19.579},
{"position": [40.64293, -8.64675], "speed": 22.696},
{"position": [40.64281, -8.64676], "speed": 10.294},
{"position": [40.64289, -8.64658], "speed": 0.142},
{"position": [40.64292, -8.64514], "speed": 6.784},
{"position": [40.64283, -8.64612], "speed": 20.705},
{"position": [40.64274, -8.64482], "speed": 21.96},
{"position": [40.64288, -8.64479], "speed": 8.751},
{"position": [40.64274, -8.64704], "speed": 0.003},
{"position": [40.64279, -8.64687], "speed": 8.248},
{"position": [40.64289, -8.64679], "speed": 21.674},
{"position": [40.642948, -8.644567], "speed": 0},
{"position": [40.642948, -8.644567], "speed": 0},
{"position": [40.64376, -8.64328], "speed": 0.735},
{"position": [40.64375, -8.64349], "speed": 8.164},
{"position": [40.64306, -8.64391], "speed": 29.548},
{"position": [40.64354, -8.64184], "speed": 34.25},
{"position": [40.64329, -8.64393], "speed": 15.535},
{"position": [40.64313, -8.64181], "speed": 0.214},
{"position": [40.64295, -8.64118], "speed": 10.238},
{"position": [40.64355, -8.64289], "speed": 31.245},
{"position": [40.64296, -8.64354], "speed": 33.139},
{"position": [40.64333, -8.64297], "speed": 13.207},
{"position": [40.64302, -8.64333], "speed": 0.004},
{"position": [40.64371, -8.64328], "speed": 12.447},
{"position": [40.643799, -8.641053], "speed": 0},
{"position": [40.643799, -8.641053], "speed": 0},
{"position": [40.64604, -8.6386], "speed": 0.316},
{"position": [40.64632, -8.63755], "speed": 3.512},
{"position": [40.64538, -8.64027], "speed": 12.71},
{"position": [40.645, -8.63761], "speed": 14.733},
{"position": [40.64494, -8.63604], "speed": 6.682},
{"position": [40.64465, -8.63994], "speed": 0.092},
{"position": [40.64651, -8.6399], "speed": 4.404},
{"position": [40.64389, -8.64024], "speed": 13.44},
{"position": [40.64501, -8.63507], "speed": 14.255},
{"position": [40.64559, -8.63971], "speed": 5.681},
{"position": [40.6456, -8.63568], "speed": 0.002},
{"position": [40.64479, -8.63625], "speed": 5.354},
{"position": [40.64522, -8.63667], "speed": 14.07},
{"position": [40.64505, -8.64056], "speed": 13.662},
{"position": [40.64527, -8.63906], "speed": 4.715},
{"position": [40.64633, -8.63852], "speed": 0.047},
{"position": [40.64453, -8.63508], "speed": 6.346},
{"position": [40.64539, -8.63561], "speed": 14.587},
{"position": [40.64618, -8.6351], "speed": 12.964},
{"position": [40.64424, -8.63636], "speed": 3.802},
{"position": [40.64481, -8.63546], "speed": 0.227},
{"position": [40.64438, -8.63811], "speed": 7.361},
{"position": [40.64443, -8.64064], "speed": 14.983},
{"position": [40.64578, -8.63591], "speed": 12.173},
{"position": [40.64662, -8.63635], "speed": 2.957},
{"position": [40.6449, -8.63562], "speed": 0.538},
{"position": [40.6464, -8.64045], "speed": 8.382},
{"position": [40.64521, -8.64037], "speed": 15.251},
{"position": [40.64411, -8.63776], "speed": 11.304},
{"position": [40.64564, -8.63914], "speed": 2.196},
{"position": [40.64639, -8.63556], "speed": 0.976},
{"position": [40.64389, -8.63878], "speed": 9.392},
{"position": [40.64561, -8.63557], "speed": 15.386},
{"position": [40.6445, -8.63552], "speed": 10.371},
{"position": [40.64628, -8.63976], "speed": 1.532},
{"position": [40.64397, -8.63536], "speed": 1.531},
{"position": [40.64433, -8.63553], "speed": 10.371},
{"position": [40.64543, -8.63599], "speed": 15.386},
{"position": [40.6456, -8.64044], "speed": 9.392},
{"position": [40.64665, -8.63856], "speed": 0.976},
{"position": [40.64396, -8.63754], "speed": 2.196},
{"position": [40.64666, -8.6391], "speed": 11.304},
{"position": [40.6462, -8.63675], "speed": 15.251},
{"position": [40.64551, -8.64021], "speed": 8.382},
{"position": [40.64558, -8.64081], "speed": 0.538},
{"position": [40.64497, -8.63957], "speed": 2.957},
{"position": [40.64407, -8.63744], "speed": 12.173},
{"position": [40.64602, -8.63663], "speed": 14.983},
{"position": [40.64638, -8.63807], "speed": 7.361},
{"position": [40.64621, -8.63679], "speed": 0.227},
{"position": [40.64629, -8.63925], "speed": 3.802},
{"position": [40.6445, -8.63692], "speed": 12.964},
{"position": [40.64553, -8.63814], "speed": 14.587},
{"position": [40.64541, -8.63821], "speed": 6.346},
{"position": [40.64474, -8.63659], "speed": 0.047},
{"position": [40.64536, -8.6392], "speed": 4.715},
{"position": [40.646689, -8.635015], "speed": 0},
{"position": [40.646689, -8.635015], "speed": 0},
{"position": [40.64707, -8.63415], "speed": 0.502},
{"position": [40.64701, -8.63477], "speed": 5.577},
{"position": [40.64682, -8.63342], "speed": 20.186},
{"position": [40.64704, -8.63485], "speed": 23.399},
{"position": [40.64715, -8.63382], "speed": 10.613},
{"position": [40.6467, -8.63498], "speed": 0.146},
{"position": [40.64724, -8.63462], "speed": 6.994},
{"position": [40.64705, -8.63361], "speed": 21.346},
{"position": [40.64718, -8.63354], "speed": 22.64},
{"position": [40.64676, -8.63407], "speed": 9.022},
{"position": [40.647377, -8.633132], "speed": 0},
{"position": [40.647377, -8.633132], "speed": 0},
{"position": [40.64742, -8.63291], "speed": 0.057},
{"position": [40.64741, -8.63299], "speed": 0.634},
{"position": [40.64741, -8.63313], "speed": 2.294},
{"position": [40.6475, -8.633], "speed": 2.659},
{"position": [40.6475, -8.63307], "speed": 1.206},
{"position": [40.64743, -8.63298], "speed": 0.017},
{"position": [40.64739, -8.63294], "speed": 0.795},
{"position": [40.6474, -8.63308], "speed": 2.425},
{"position": [40.64746, -8.63296], "speed": 2.572},
{"position": [40.64741, -8.63295], "speed": 1.025},
{"position": [40.64747, -8.63299], "speed": 0.0},
{"position": [40.64748, -8.63296], "speed": 0.966},
{"position": [40.647499, -8.632877], "speed": 0},
{"position": [40.647499, -8.632877], "speed": 0},
{"position": [40.64365, -8.62838], "speed": 1.207},
{"position": [40.64476, -8.62938], "speed": 13.401},
{"position": [40.64606, -8.62577], "speed": 48.5},
{"position": [40.6443, -8.63222], "speed": 56.219},
{"position": [40.64377, -8.62182], "speed": 25.499},
{"position": [40.64747, -8.62266], "speed": 0.352},
{"position": [40.64663, -8.62634], "speed": 16.805},
{"position": [40.64276, -8.62629], "speed": 51.287},
{"position": [40.64499, -8.6268], "speed": 54.396},
{"position": [40.64429, -8.62377], "speed": 21.678},
{"position": [40.64302, -8.62619], "speed": 0.007},
{"position": [40.64371, -8.62837], "speed": 20.431},
{"position": [40.6469, -8.62896], "speed": 53.688},
{"position": [40.64592, -8.62618], "speed": 52.133},
{"position": [40.64667, -8.62637], "speed": 17.992},
{"position": [40.64544, -8.63107], "speed": 0.18},
{"position": [40.64266, -8.62335], "speed": 24.214},
{"position": [40.64471, -8.62272], "speed": 55.662},
{"position": [40.64313, -8.63001], "speed": 49.469},
{"position": [40.64443, -8.63265], "speed": 14.507},
{"position": [40.64562, -8.62673], "speed": 0.866},
{"position": [40.64337, -8.6309], "speed": 28.089},
{"position": [40.64654, -8.62357], "speed": 57.174},
{"position": [40.64279, -8.6303], "speed": 46.452},
{"position": [40.64486, -8.62855], "speed": 11.284},
{"position": [40.64417, -8.62607], "speed": 2.054},
{"position": [40.64257, -8.621762], "speed": 0},
{"position": [40.64257, -8.621762], "speed": 0},
{"position": [40.65022, -8.59348], "speed": 0.439},
{"position": [40.64566, -8.61736], "speed": 4.873},
{"position": [40.65074, -8.61675], "speed": 17.636},
{"position": [40.65038, -8.59119], "speed": 20.443},
{"position": [40.64518, -8.60215], "speed": 9.272},
{"position": [40.6478, -8.60715], "speed": 0.128},
{"position": [40.64894, -8.61644], "speed": 6.111},
{"position": [40.64434, -8.61762], "speed": 18.65},
{"position": [40.65161, -8.60436], "speed": 19.78},
{"position": [40.64882, -8.59621], "speed": 7.883},
{"position": [40.64366, -8.60682], "speed": 0.003},
{"position": [40.651, -8.59082], "speed": 7.429},
{"position": [40.6521, -8.61532], "speed": 19.523},
{"position": [40.64916, -8.61257], "speed": 18.957},
{"position": [40.64514, -8.61802], "speed": 6.543},
{"position": [40.64357, -8.59186], "speed": 0.065},
{"position": [40.64371, -8.60819], "speed": 8.805},
{"position": [40.64824, -8.61882], "speed": 20.241},
{"position": [40.65137, -8.61624], "speed": 17.989},
{"position": [40.65052, -8.6207], "speed": 5.275},
{"position": [40.64702, -8.59356], "speed": 0.315},
{"position": [40.64787, -8.60852], "speed": 10.214},
{"position": [40.64262, -8.60472], "speed": 20.791},
{"position": [40.64613, -8.61942], "speed": 16.892},
{"position": [40.65154, -8.60586], "speed": 4.103},
{"position": [40.64542, -8.59613], "speed": 0.747},
{"position": [40.64511, -8.59778], "speed": 11.631},
{"position": [40.64902, -8.60271], "speed": 21.163},
{"position": [40.65009, -8.60868], "speed": 15.686},
{"position": [40.65196, -8.6138], "speed": 3.047},
{"position": [40.64466, -8.60109], "speed": 1.354},
{"position": [40.64262, -8.59333], "speed": 13.032},
{"position": [40.64998, -8.60486], "speed": 21.35},
{"position": [40.65181, -8.59422], "speed": 14.391},
{"position": [40.65214, -8.59509], "speed": 2.125},
{"position": [40.65158, -8.60958], "speed": 2.125},
{"position": [40.65114, -8.60057], "speed": 14.391},
{"position": [40.64888, -8.61217], "speed": 21.35},
{"position": [40.64841, -8.61568], "speed": 13.032},
{"position": [40.64683, -8.59483], "speed": 1.354},
{"position": [40.6494, -8.6137], "speed": 3.047},
{"position": [40.64858, -8.59839], "speed": 15.685},
{"position": [40.64298, -8.61852], "speed": 21.163},
{"position": [40.64305, -8.60623], "speed": 11.632},
{"position": [40.65187, -8.59266], "speed": 0.747},
{"position": [40.64535, -8.59635], "speed": 4.103},
{"position": [40.64846, -8.59998], "speed": 16.892},
{"position": [40.64701, -8.61258], "speed": 20.791},
{"position": [40.64706, -8.5967], "speed": 10.214},
{"position": [40.64434, -8.59646], "speed": 0.315},
{"position": [40.64765, -8.60808], "speed": 5.275},
{"position": [40.65095, -8.60894], "speed": 17.989},
{"position": [40.64459, -8.60259], "speed": 20.241},
{"position": [40.64923, -8.61946], "speed": 8.806},
{"position": [40.65193, -8.62052], "speed": 0.065},
{"position": [40.6492, -8.60942], "speed": 6.542},
{"position": [40.65012, -8.60881], "speed": 18.957},
{"position": [40.64743, -8.60954], "speed": 19.523},
{"position": [40.64325, -8.59602], "speed": 7.43},
{"position": [40.64556, -8.60667], "speed": 0.003},
{"position": [40.6461, -8.59628], "speed": 7.883},
{"position": [40.64314, -8.59505], "speed": 19.78},
{"position": [40.64875, -8.6029], "speed": 18.65},
{"position": [40.64735, -8.59027], "speed": 6.111},
{"position": [40.64706, -8.60559], "speed": 0.128},
{"position": [40.64427, -8.61281], "speed": 9.272},
{"position": [40.64924, -8.60238], "speed": 20.443},
{"position": [40.64624, -8.59238], "speed": 17.637},
{"position": [40.64326, -8.59618], "speed": 4.873},
{"position": [40.652, -8.61894], "speed": 0.439},
{"position": [40.64982, -8.60855], "speed": 10.687},
{"position": [40.65047, -8.61257], "speed": 20.935},
{"position": [40.64376, -8.60534], "speed": 16.501},
{"position": [40.64488, -8.61313], "speed": 3.738},
{"position": [40.64616, -8.60406], "speed": 0.93},
{"position": [40.64855, -8.59192], "speed": 12.101},
{"position": [40.64957, -8.60883], "speed": 21.246},
{"position": [40.64648, -8.59603], "speed": 15.263},
{"position": [40.64926, -8.61021], "speed": 2.724},
{"position": [40.65113, -8.59301], "speed": 1.593},
{"position": [40.65189, -8.59598], "speed": 13.491},
{"position": [40.64564, -8.60783], "speed": 21.371},
{"position": [40.64357, -8.59983], "speed": 13.945},
{"position": [40.65036, -8.61883], "speed": 1.851},
{"position": [40.65125, -8.59833], "speed": 2.416},
{"position": [40.64453, -8.60359], "speed": 14.831},
{"position": [40.64303, -8.60618], "speed": 21.308},
{"position": [40.64643, -8.59885], "speed": 12.569},
{"position": [40.64637, -8.59455], "speed": 1.133},
{"position": [40.65089, -8.59757], "speed": 3.385},
{"position": [40.64789, -8.60894], "speed": 16.098},
{"position": [40.6462, -8.59501], "speed": 21.059},
{"position": [40.64568, -8.59096], "speed": 11.16},
{"position": [40.64874, -8.60558], "speed": 0.583},
{"position": [40.64748, -8.60704], "speed": 4.482},
{"position": [40.64712, -8.6026], "speed": 17.27},
{"position": [40.64493, -8.61824], "speed": 20.627},
{"position": [40.64621, -8.59529], "speed": 9.743},
{"position": [40.64304, -8.59224], "speed": 0.211},
{"position": [40.65146, -8.61681], "speed": 5.688},
{"position": [40.64445, -8.61281], "speed": 18.326},
{"position": [40.6463, -8.59098], "speed": 20.02},
{"position": [40.64824, -8.59854], "speed": 8.342},
{"position": [40.6477, -8.62173], "speed": 0.024},
{"position": [40.64371, -8.593], "speed": 6.982},
{"position": [40.6479, -8.62122], "speed": 19.248},
{"position": [40.64361, -8.59335], "speed": 19.249},
{"position": [40.64477, -8.60055], "speed": 6.983},
{"position": [40.64594, -8.61078], "speed": 0.023},
{"position": [40.64547, -8.61856], "speed": 8.341},
{"position": [40.64643, -8.62142], "speed": 20.02},
{"position": [40.64599, -8.60545], "speed": 18.327},
{"position": [40.64413, -8.61089], "speed": 5.689},
{"position": [40.6499, -8.60803], "speed": 0.211},
{"position": [40.64688, -8.60627], "speed": 9.742},
{"position": [40.65005, -8.60864], "speed": 20.627},
{"position": [40.65002, -8.61231], "speed": 17.271},
{"position": [40.6509, -8.61267], "speed": 4.482},
{"position": [40.64374, -8.59221], "speed": 0.583},
{"position": [40.64531, -8.59363], "speed": 11.159},
{"position": [40.64785, -8.59846], "speed": 21.059},
{"position": [40.64712, -8.6021], "speed": 16.099},
{"position": [40.65196, -8.59989], "speed": 3.385},
{"position": [40.64794, -8.59149], "speed": 1.133},
{"position": [40.64562, -8.62058], "speed": 12.568},
{"position": [40.64665, -8.60003], "speed": 21.308},
{"position": [40.64912, -8.59255], "speed": 14.832},
{"position": [40.64659, -8.61265], "speed": 2.417},
{"position": [40.64312, -8.60087], "speed": 1.85},
{"position": [40.64547, -8.61471], "speed": 13.944},
{"position": [40.65177, -8.59583], "speed": 21.371},
{"position": [40.65102, -8.615], "speed": 13.491},
{"position": [40.64666, -8.59964], "speed": 1.594},
{"position": [40.6442, -8.60942], "speed": 2.724},
{"position": [40.64995, -8.61804], "speed": 15.262},
{"position": [40.64862, -8.61223], "speed": 21.246},
{"position": [40.64915, -8.61669], "speed": 12.102},
{"position": [40.6521, -8.59448], "speed": 0.931},
{"position": [40.64674, -8.59983], "speed": 3.737},
{"position": [40.64281, -8.61234], "speed": 16.5},
{"position": [40.64428, -8.60566], "speed": 20.935},
{"position": [40.64773, -8.60052], "speed": 10.688},
{"position": [40.65055, -8.60086], "speed": 0.439},
{"position": [40.64692, -8.60035], "speed": 4.872},
{"position": [40.64891, -8.59284], "speed": 17.636},
{"position": [40.64291, -8.60807], "speed": 20.444},
{"position": [40.64379, -8.59842], "speed": 9.273},
{"position": [40.65031, -8.60174], "speed": 0.128},
{"position": [40.64341, -8.59153], "speed": 6.11},
{"position": [40.65049, -8.61897], "speed": 18.649},
{"position": [40.6441, -8.59474], "speed": 19.781},
{"position": [40.64616, -8.61571], "speed": 7.884},
{"position": [40.6516, -8.61218], "speed": 0.003},
{"position": [40.64484, -8.59812], "speed": 7.429},
{"position": [40.64516, -8.61813], "speed": 19.523},
{"position": [40.64774, -8.6046], "speed": 18.958},
{"position": [40.6457, -8.61776], "speed": 6.543},
{"position": [40.64897, -8.60048], "speed": 0.065},
{"position": [40.64347, -8.61929], "speed": 8.805},
{"position": [40.64702, -8.62057], "speed": 20.241},
{"position": [40.65165, -8.61011], "speed": 17.989},
{"position": [40.64554, -8.59428], "speed": 5.276},
{"position": [40.65211, -8.61109], "speed": 0.315},
{"position": [40.65184, -8.60242], "speed": 10.213},
{"position": [40.64863, -8.59306], "speed": 20.79},
{"position": [40.64768, -8.60123], "speed": 16.892},
{"position": [40.65211, -8.60254], "speed": 4.104},
{"position": [40.65216, -8.6149], "speed": 0.747},
{"position": [40.65199, -8.59657], "speed": 11.631},
{"position": [40.64833, -8.613], "speed": 21.162},
{"position": [40.64486, -8.60101], "speed": 15.686},
{"position": [40.65151, -8.61508], "speed": 3.048},
{"position": [40.643, -8.60465], "speed": 1.354},
{"position": [40.64958, -8.5995], "speed": 13.031},
{"position": [40.65136, -8.59996], "speed": 21.35},
{"position": [40.64894, -8.61258], "speed": 14.392},
{"position": [40.64995, -8.5929], "speed": 2.126},
{"position": [40.65196, -8.59716], "speed": 2.125},
{"position": [40.65077, -8.59807], "speed": 14.391},
{"position": [40.64989, -8.61416], "speed": 21.35},
{"position": [40.64353, -8.59745], "speed": 13.033},
{"position": [40.64948, -8.59764], "speed": 1.354},
{"position": [40.64275, -8.59885], "speed": 3.046},
{"position": [40.6473, -8.61559], "speed": 15.685},
{"position": [40.65225, -8.60777], "speed": 21.163},
{"position": [40.64457, -8.60916], "speed": 11.632},
{"position": [40.64712, -8.60588], "speed": 0.747},
{"position": [40.64881, -8.60737], "speed": 4.103},
{"position": [40.64849, -8.60348], "speed": 16.891},
{"position": [40.64411, -8.60935], "speed": 20.791},
{"position": [40.64671, -8.62163], "speed": 10.215},
{"position": [40.65112, -8.61626], "speed": 0.315},
{"position": [40.64791, -8.61827], "speed": 5.275},
{"position": [40.65228, -8.59166], "speed": 17.988},
{"position": [40.652285, -8.590059], "speed": 0},
{"position": [40.652285, -8.590059], "speed": 0},
{"position": [40.65357, -8.58917], "speed": 1.23},
{"position": [40.6558, -8.5819], "speed": 13.652},
{"position": [40.65299, -8.58486], "speed": 49.408},
{"position": [40.65547, -8.5798], "speed": 57.272},
{"position": [40.65432, -8.58667], "speed": 25.977},
{"position": [40.65507, -8.58308], "speed": 0.358},
{"position": [40.65285, -8.58646], "speed": 17.12},
{"position": [40.65552, -8.58433], "speed": 52.247},
{"position": [40.65503, -8.58071], "speed": 55.415},
{"position": [40.65286, -8.58354], "speed": 22.084},
{"position": [40.65344, -8.58163], "speed": 0.007},
{"position": [40.65322, -8.58516], "speed": 20.813},
{"position": [40.65266, -8.5838], "speed": 54.694},
{"position": [40.65287, -8.58274], "speed": 53.109},
{"position": [40.6533, -8.58786], "speed": 18.329},
{"position": [40.65242, -8.58128], "speed": 0.183},
{"position": [40.65445, -8.58837], "speed": 24.668},
{"position": [40.6557, -8.58084], "speed": 56.705},
{"position": [40.65534, -8.58372], "speed": 50.396},
{"position": [40.65277, -8.58851], "speed": 14.779},
{"position": [40.6537, -8.58618], "speed": 0.882},
{"position": [40.65284, -8.58661], "speed": 28.615},
{"position": [40.65444, -8.58819], "speed": 58.245},
{"position": [40.65581, -8.579432], "speed": 0},
{"position": [40.65581, -8.579432], "speed": 0},
{"position": [40.6729, -8.58224], "speed": 0.871},
{"position": [40.65656, -8.58362], "speed": 9.674},
{"position": [40.66524, -8.5801], "speed": 35.012},
{"position": [40.65693, -8.58515], "speed": 40.584},
{"position": [40.66579, -8.58414], "speed": 18.408},
{"position": [40.65699, -8.58348], "speed": 0.254},
{"position": [40.67561, -8.58336], "speed": 12.131},
{"position": [40.66202, -8.58555], "speed": 37.024},
{"position": [40.66126, -8.58229], "speed": 39.268},
{"position": [40.65744, -8.58139], "speed": 15.649},
{"position": [40.666, -8.58175], "speed": 0.005},
{"position": [40.65739, -8.58874], "speed": 14.749},
{"position": [40.658, -8.58922], "speed": 38.757},
{"position": [40.65669, -8.57978], "speed": 37.634},
{"position": [40.66434, -8.58877], "speed": 12.989},
{"position": [40.6706, -8.5882], "speed": 0.13},
{"position": [40.66616, -8.58249], "speed": 17.48},
{"position": [40.67442, -8.58231], "speed": 40.182},
{"position": [40.665, -8.58211], "speed": 35.712},
{"position": [40.66172, -8.58317], "speed": 10.473},
{"position": [40.66073, -8.58536], "speed": 0.625},
{"position": [40.65703, -8.58907], "speed": 20.277},
{"position": [40.66723, -8.58793], "speed": 41.274},
{"position": [40.65755, -8.58359], "speed": 33.534},
{"position": [40.66159, -8.59003], "speed": 8.146},
{"position": [40.67449, -8.57989], "speed": 1.483},
{"position": [40.66944, -8.58501], "speed": 23.09},
{"position": [40.67477, -8.58463], "speed": 42.012},
{"position": [40.66432, -8.58097], "speed": 31.139},
{"position": [40.67014, -8.58001], "speed": 6.049},
{"position": [40.66757, -8.58062], "speed": 2.688},
{"position": [40.66118, -8.58786], "speed": 25.871},
{"position": [40.65737, -8.58274], "speed": 42.385},
{"position": [40.65991, -8.58841], "speed": 28.57},
{"position": [40.66849, -8.58864], "speed": 4.219},
{"position": [40.66852, -8.58289], "speed": 4.219},
{"position": [40.6745, -8.58624], "speed": 28.569},
{"position": [40.66251, -8.58147], "speed": 42.385},
{"position": [40.65735, -8.58164], "speed": 25.872},
{"position": [40.6663, -8.58659], "speed": 2.688},
{"position": [40.67135, -8.58702], "speed": 6.049},
{"position": [40.67187, -8.58641], "speed": 31.139},
{"position": [40.66002, -8.58832], "speed": 42.012},
{"position": [40.66243, -8.58664], "speed": 23.091},
{"position": [40.66126, -8.58632], "speed": 1.483},
{"position": [40.66732, -8.58383], "speed": 8.145},
{"position": [40.66178, -8.58916], "speed": 33.533},
{"position": [40.65747, -8.58413], "speed": 41.274},
{"position": [40.65619, -8.58064], "speed": 20.278},
{"position": [40.66869, -8.58116], "speed": 0.625},
{"position": [40.67375, -8.58978], "speed": 10.472},
{"position": [40.66989, -8.58292], "speed": 35.711},
{"position": [40.6611, -8.58482], "speed": 40.183},
{"position": [40.66357, -8.58258], "speed": 17.481},
{"position": [40.66941, -8.58249], "speed": 0.13},
{"position": [40.65945, -8.5828], "speed": 12.988},
{"position": [40.6691, -8.5807], "speed": 37.634},
{"position": [40.67256, -8.58904], "speed": 38.758},
{"position": [40.66689, -8.58043], "speed": 14.75},
{"position": [40.66882, -8.58393], "speed": 0.005},
{"position": [40.65727, -8.5852], "speed": 15.649},
{"position": [40.6588, -8.58388], "speed": 39.268},
{"position": [40.66603, -8.57959], "speed": 37.024},
{"position": [40.66842, -8.58245], "speed": 12.132},
{"position": [40.66588, -8.58305], "speed": 0.254},
{"position": [40.66985, -8.58254], "speed": 18.407},
{"position": [40.66132, -8.58996], "speed": 40.584},
{"position": [40.67143, -8.58386], "speed": 35.012},
{"position": [40.67371, -8.59004], "speed": 9.674},
{"position": [40.66637, -8.58909], "speed": 0.871},
{"position": [40.67044, -8.58838], "speed": 21.215},
{"position": [40.6664, -8.58866], "speed": 41.56},
{"position": [40.66112, -8.58992], "speed": 32.758},
{"position": [40.67133, -8.5804], "speed": 7.42},
{"position": [40.66905, -8.58291], "speed": 1.847},
{"position": [40.66331, -8.57979], "speed": 24.023},
{"position": [40.66602, -8.58481], "speed": 42.177},
{"position": [40.6637, -8.58819], "speed": 30.3},
{"position": [40.66248, -8.58757], "speed": 5.408},
{"position": [40.67185, -8.58963], "speed": 3.163},
{"position": [40.6705, -8.58673], "speed": 26.782},
{"position": [40.675744, -8.590225], "speed": 0},
{"position": [40.675744, -8.590225], "speed": 0},
{"position": [40.67984, -8.59132], "speed": 0.497},
{"position": [40.68029, -8.59351], "speed": 5.52},
{"position": [40.67701, -8.59109], "speed": 19.977},
{"position": [40.67658, -8.59573], "speed": 23.157},
{"position": [40.67927, -8.59859], "speed": 10.503},
{"position": [40.67588, -8.59282], "speed": 0.145},
{"position": [40.67769, -8.59219], "speed": 6.922},
{"position": [40.68066, -8.59093], "speed": 21.125},
{"position": [40.67992, -8.59613], "speed": 22.406},
{"position": [40.67769, -8.59621], "speed": 8.929},
{"position": [40.68036, -8.59563], "speed": 0.003},
{"position": [40.67836, -8.59723], "speed": 8.415},
{"position": [40.68016, -8.59869], "speed": 22.114},
{"position": [40.67804, -8.59441], "speed": 21.473},
{"position": [40.67647, -8.5959], "speed": 7.411},
{"position": [40.67628, -8.59331], "speed": 0.074},
{"position": [40.68062, -8.59645], "speed": 9.974},
{"position": [40.67647, -8.59575], "speed": 22.927},
{"position": [40.67786, -8.59809], "speed": 20.376},
{"position": [40.68074, -8.59275], "speed": 5.976},
{"position": [40.68019, -8.59122], "speed": 0.357},
{"position": [40.67759, -8.59156], "speed": 11.57},
{"position": [40.67807, -8.59397], "speed": 23.55},
{"position": [40.67634, -8.59389], "speed": 19.134},
{"position": [40.67725, -8.59636], "speed": 4.648},
{"position": [40.67586, -8.59322], "speed": 0.846},
{"position": [40.6772, -8.5976], "speed": 13.175},
{"position": [40.67659, -8.59839], "speed": 23.971},
{"position": [40.6809, -8.59148], "speed": 17.767},
{"position": [40.6779, -8.59619], "speed": 3.452},
{"position": [40.67914, -8.5912], "speed": 1.534},
{"position": [40.67761, -8.59332], "speed": 14.761},
{"position": [40.68086, -8.59643], "speed": 24.184},
{"position": [40.67778, -8.59389], "speed": 16.302},
{"position": [40.68043, -8.59788], "speed": 2.407},
{"position": [40.67866, -8.59668], "speed": 2.407},
{"position": [40.67851, -8.59281], "speed": 16.301},
{"position": [40.67919, -8.59817], "speed": 24.184},
{"position": [40.6778, -8.59655], "speed": 14.762},
{"position": [40.67622, -8.5996], "speed": 1.534},
{"position": [40.67723, -8.59836], "speed": 3.451},
{"position": [40.67815, -8.59425], "speed": 17.767},
{"position": [40.68003, -8.59231], "speed": 23.971},
{"position": [40.67986, -8.59758], "speed": 13.175},
{"position": [40.67575, -8.59628], "speed": 0.846},
{"position": [40.67728, -8.59752], "speed": 4.648},
{"position": [40.68058, -8.5965], "speed": 19.133},
{"position": [40.67846, -8.5904], "speed": 23.55},
{"position": [40.678, -8.59604], "speed": 11.57},
{"position": [40.67674, -8.59515], "speed": 0.357},
{"position": [40.67858, -8.59536], "speed": 5.975},
{"position": [40.68002, -8.59033], "speed": 20.376},
{"position": [40.67862, -8.59581], "speed": 22.928},
{"position": [40.67737, -8.59468], "speed": 9.974},
{"position": [40.67772, -8.59945], "speed": 0.074},
{"position": [40.67842, -8.59843], "speed": 7.411},
{"position": [40.68039, -8.59516], "speed": 21.473},
{"position": [40.67623, -8.59937], "speed": 22.114},
{"position": [40.67592, -8.59339], "speed": 8.416},
{"position": [40.68091, -8.59681], "speed": 0.003},
{"position": [40.681281, -8.599817], "speed": 0}
]